django_basic_crud_generator/__init__.py
django_basic_crud_generator/__main__.py
django_basic_crud_generator/argumentParser.py
django_basic_crud_generator/django_basic_crud_generator.py
django_basic_crud_generator/templates/layout/base.tmpl
django_basic_crud_generator/templates/templates/create.tmpl
django_basic_crud_generator/templates/templates/delete.tmpl
django_basic_crud_generator/templates/templates/detail.tmpl
django_basic_crud_generator/templates/templates/list.tmpl
django_basic_crud_generator/templates/templates/update.tmpl
django_basic_crud_generator/templates/tests/create.tmpl
django_basic_crud_generator/templates/tests/delete.tmpl
django_basic_crud_generator/templates/tests/detail.tmpl
django_basic_crud_generator/templates/tests/list.tmpl
django_basic_crud_generator/templates/tests/update.tmpl
django_basic_crud_generator/templates/views/create.tmpl
django_basic_crud_generator/templates/views/delete.tmpl
django_basic_crud_generator/templates/views/detail.tmpl
django_basic_crud_generator/templates/views/list.tmpl
django_basic_crud_generator/templates/views/update.tmpl
Django_Basic_CRUD_Generator-0.2.dist-info/LICENSE
Django_Basic_CRUD_Generator-0.2.dist-info/METADATA
Django_Basic_CRUD_Generator-0.2.dist-info/WHEEL
Django_Basic_CRUD_Generator-0.2.dist-info/top_level.txt
Django_Basic_CRUD_Generator-0.2.dist-info/RECORD
