Metadata-Version: 2.1
Name: Django-Basic-CRUD-Generator
Version: 0.2
Summary: Script to generate views, templates and tests files for a given Django Model
Home-page: https://github.com/J-hanks/django_basic_crud_generator.git
Author: Joao Cunha  
Author-email: jvsdc1992@gmail.com
License: None
Keywords: django crud generator scaffolding scaffold
Platform: UNKNOWN
Classifier: Programming Language :: Python :: 3.8
Classifier: Development Status :: 3 - Alpha
Classifier: Operating System :: OS Independent
